[
    {
        "opinion_id": "13569028",
        "author": "m...2",
        "recommendation": true,
        "score": 0.8,
        "content": {
            "pl": "Na obecnym etapie powyższy produkt wykazuje stosunkowo wysoką skuteczność działania. Tak siedem punktów na dziesięć. Ważne jest aby dokładnie uszczelnić wylot z korytarzy podziemnych i dokładnie zaaplikować jednorazowo tabletki w różnych miejscach przebywania karczownika na działce. Sam jestem ciekaw jak będzie wyglądać to na większej przestrzeni czasu. Na pewno trzeba kontrolować powstawanie nowych kopcy i szybko aplikować.",
            "en": "At this stage, the above product shows relatively high effectiveness. Yes, seven points out of ten. It is important to carefully seal the outlet from underground corridors and apply the tablets carefully at one time in various places where the water vole resides on the plot. I'm curious what it will look like over a longer period of time. You definitely need to control the formation of new mounds and apply quickly."
        },
        "pros": {
            "pl": [
                "jakość",
                "wydajność"
            ],
            "en": [
                "quality",
                "efficiency"
            ]
        },
        "cons": null,
        "helpful": 1,
        "unhelpful": 1,
        "publish_date": "2020-12-13 19:38:50",
        "purchase_date": "2020-12-01 09:57:59"
    },
    {
        "opinion_id": "18466696",
        "author": "l...r",
        "recommendation": true,
        "score": 1.0,
        "content": {
            "pl": "bardzo skuteczny produkt, od dwóch lat ani kreta ani nornic. A wcześniej kopce mutanty. Trzeba bardzo przestrzegać zasad używania i daleko od wody.",
            "en": "very effective product, no moles or voles for two years. And before that, there are mounds of mutants. You have to follow the rules of use very carefully and stay away from the water."
        },
        "pros": null,
        "cons": null,
        "helpful": 1,
        "unhelpful": 0,
        "publish_date": "2024-03-06 13:48:18",
        "purchase_date": "2024-02-20 12:20:30"
    },
    {
        "opinion_id": "14492253",
        "author": "m...h",
        "recommendation": true,
        "score": 0.8,
        "content": {
            "pl": "działa całkiem skutecznie, jeśli dobrze zaaplikowany potrafi unieszkodliwić szkodniki lub je skutecznie wykurzyć...",
            "en": "it works quite effectively if, when applied well, it can neutralize pests or expel them effectively..."
        },
        "pros": {
            "pl": [
                "jakość",
                "skuteczność",
                "wydajność"
            ],
            "en": [
                "quality",
                "effectiveness",
                "efficiency"
            ]
        },
        "cons": null,
        "helpful": 0,
        "unhelpful": 0,
        "publish_date": "2021-05-21 08:48:24",
        "purchase_date": "2021-05-10 12:57:47"
    },
    {
        "opinion_id": "13145499",
        "author": "l...k",
        "recommendation": true,
        "score": 1.0,
        "content": {
            "pl": "Produkt działa bardzo szybko. Efekty użycia wręcz spektakularne, bo kretowiny przestały się pojawiać.",
            "en": "The product works very quickly. The effects of use are spectacular, because mole spots stopped appearing."
        },
        "pros": {
            "pl": [
                "jakość",
                "skuteczność",
                "wydajność"
            ],
            "en": [
                "quality",
                "effectiveness",
                "efficiency"
            ]
        },
        "cons": null,
        "helpful": 0,
        "unhelpful": 0,
        "publish_date": "2020-09-30 14:50:39",
        "purchase_date": "2020-09-28 13:48:58"
    },
    {
        "opinion_id": "18505505",
        "author": "m...1",
        "recommendation": true,
        "score": 1.0,
        "content": {
            "pl": "Otrzymany produkt zgodny ze zdjęciem. Dobrze spakowany. Jeszcze nie przetestowany.",
            "en": "The product received matches the photo. Well packed. Not yet tested."
        },
        "pros": null,
        "cons": null,
        "helpful": 0,
        "unhelpful": 0,
        "publish_date": "2024-03-19 16:52:01",
        "purchase_date": "2024-03-15 14:35:37"
    },
    {
        "opinion_id": "16303146",
        "author": "g...6",
        "recommendation": true,
        "score": 1.0,
        "content": {
            "pl": "Super skuteczny środek na krety . teraz mam spokój z kopcami.polecam..grazyna.",
            "en": "A super effective remedy for moles. now I have peace with the mounds. I recommend it... Grazyna."
        },
        "pros": {
            "pl": [
                "jakość",
                "skuteczność",
                "wydajność"
            ],
            "en": [
                "quality",
                "effectiveness",
                "efficiency"
            ]
        },
        "cons": null,
        "helpful": 0,
        "unhelpful": 0,
        "publish_date": "2022-07-11 11:49:39",
        "purchase_date": "2022-06-06 14:33:48"
    },
    {
        "opinion_id": "15107266",
        "author": "c...1",
        "recommendation": true,
        "score": 1.0,
        "content": {
            "pl": "opakowanie super trudno otworzyć ale skutecznie zatrzymuje gaz w butelce",
            "en": "the packaging is very difficult to open, but it effectively retains the gas in the bottle"
        },
        "pros": {
            "pl": [
                "jakość",
                "skuteczność",
                "wydajność"
            ],
            "en": [
                "quality",
                "effectiveness",
                "efficiency"
            ]
        },
        "cons": null,
        "helpful": 0,
        "unhelpful": 1,
        "publish_date": "2021-10-21 09:30:29",
        "purchase_date": "2021-10-17 11:48:18"
    },
    {
        "opinion_id": "14595384",
        "author": "r...k",
        "recommendation": true,
        "score": 0.8,
        "content": {
            "pl": "Działa, kret ucieka. Niestety po dwóch tygodniach powrócił  : (",
            "en": "It works, the mole escapes. Unfortunately, it came back after two weeks :("
        },
        "pros": {
            "pl": [
                "jakość",
                "wydajność"
            ],
            "en": [
                "quality",
                "efficiency"
            ]
        },
        "cons": null,
        "helpful": 0,
        "unhelpful": 0,
        "publish_date": "2021-06-14 06:31:11",
        "purchase_date": "2021-05-21 10:00:02"
    },
    {
        "opinion_id": "15346481",
        "author": "b...0",
        "recommendation": true,
        "score": 1.0,
        "content": {
            "pl": "super środek dziala niezawodnie. Wszystkie krety się wyniosły.",
            "en": "great product works reliably. All the moles have moved out."
        },
        "pros": {
            "pl": [
                "wydajność"
            ],
            "en": [
                "efficiency"
            ]
        },
        "cons": null,
        "helpful": 0,
        "unhelpful": 0,
        "publish_date": "2021-12-10 21:29:13",
        "purchase_date": "2021-11-22 10:56:18"
    },
    {
        "opinion_id": "11025915",
        "author": "Rysiek",
        "recommendation": true,
        "score": 0.9,
        "content": {
            "pl": "skuteczny",
            "en": "effective"
        },
        "pros": {
            "pl": [
                "jakość",
                "skuteczność",
                "wydajność"
            ],
            "en": [
                "quality",
                "effectiveness",
                "efficiency"
            ]
        },
        "cons": null,
        "helpful": 0,
        "unhelpful": 0,
        "publish_date": "2019-10-02 13:03:18",
        "purchase_date": "2019-09-01 19:52:29"
    }
]